README.md
setup.py
httpantry/__init__.py
httpantry/command_line.py
httpantry/http_proxy_server.py
httpantry/parse_configuration.py
httpantry/proxy_database.py
httpantry/requests_wrapper.py
httpantry.egg-info/PKG-INFO
httpantry.egg-info/SOURCES.txt
httpantry.egg-info/dependency_links.txt
httpantry.egg-info/entry_points.txt
httpantry.egg-info/requires.txt
httpantry.egg-info/top_level.txt