Metadata-Version: 2.1
Name: httpantry
Version: 0.0.6
Summary: Caches HTTP requests for faster, more efficient development
Home-page: https://github.com/RowenFelt/httpantry
Author: Rowen Felt, Zebediah Millslagle
Author-email: rowenfelt@gmail.com, zmillslagle@gmail.com
License: UNKNOWN
Platform: UNKNOWN
Classifier: Programming Language :: Python :: 3
Classifier: License :: OSI Approved :: MIT License
Classifier: Operating System :: OS Independent
